tests/__init__.py
tests/conftest.py
tests/test_viadot.py
tests/integration/__init__.py
tests/integration/test_azuresql.py
tests/integration/test_azurestorage.py
tests/integration/test_bigquery.py
tests/integration/test_business_core.py
tests/integration/test_cloud_for_customers.py
tests/integration/test_customer_gauge.py
tests/integration/test_epicor.py
tests/integration/test_eurostat.py
tests/integration/test_genesys.py
tests/integration/test_hubspot.py
tests/integration/test_mediatool.py
tests/integration/test_mindful.py
tests/integration/test_mysql.py
tests/integration/test_salesforce.py
tests/integration/test_sap_bw.py
tests/integration/test_sap_rfc.py
tests/integration/test_sftp.py
tests/integration/test_sharepoint.py
tests/integration/test_supermetrics.py
tests/integration/test_supermetrics_to_azuresql.py
tests/integration/test_tm1.py
tests/integration/test_uk_carbon_intensity.py
tests/integration/test_vid_club.py
tests/integration/flows/__init__.py
tests/integration/flows/test_adls_gen1_to_azure_sql.py
tests/integration/flows/test_adls_gen1_to_azure_sql_new.py
tests/integration/flows/test_adls_gen1_to_gen2.py
tests/integration/flows/test_adls_to_azure_sql.py
tests/integration/flows/test_aselite_to_adls.py
tests/integration/flows/test_azure_sql_transform.py
tests/integration/flows/test_bigquery_to_adls.py
tests/integration/flows/test_cloud_for_customers_report_to_adls.py
tests/integration/flows/test_customer_gauge_to_adls.py
tests/integration/flows/test_duck_transform.py
tests/integration/flows/test_duckdb_to_sql_server.py
tests/integration/flows/test_duckdb_transform.py
tests/integration/flows/test_epicor_to_duckdb.py
tests/integration/flows/test_eurostat_to_adls.py
tests/integration/flows/test_flow_of_flows.py
tests/integration/flows/test_hubspot_to_adls.py
tests/integration/flows/test_mediatool_to_adls.py
tests/integration/flows/test_multiple_flows.py
tests/integration/flows/test_mysql_to_adls.py
tests/integration/flows/test_prefect_logs.py
viadot-0.4.24.dist-info/LICENSE
viadot-0.4.24.dist-info/METADATA
viadot-0.4.24.dist-info/WHEEL
viadot-0.4.24.dist-info/top_level.txt
viadot-0.4.24.dist-info/RECORD
