Metadata-Version: 2.1
Name: viadot
Version: 0.4.24
Summary: A simple data ingestion library to guide data flows from some places to other places
Home-page: https://github.com/dyvenia/viadot
Author: Alessio Civitillo
License: UNKNOWN
Platform: UNKNOWN
Classifier: Programming Language :: Python :: 3
Classifier: License :: OSI Approved :: MIT License
Classifier: Operating System :: OS Independent
